setup.py
pyJMP/__init__.py
pyJMP/pyJMP.py
pyJMP.egg-info/PKG-INFO
pyJMP.egg-info/SOURCES.txt
pyJMP.egg-info/dependency_links.txt
pyJMP.egg-info/not-zip-safe
pyJMP.egg-info/top_level.txt