Metadata-Version: 1.0
Name: pyJMP
Version: 0.1.0
Summary: python API to SAS JMP
Home-page: https://github.com/spidezad/pyJMP
Author: Tan Kok Hua
Author-email: kokhua81@gmail.com
License: UNKNOWN
Platform: UNKNOWN
